gotennet_pytorch/__init__.py
gotennet_pytorch/gotennet.py
gotennet_pytorch/tensor_typing.py
gotennet_pytorch-0.3.1.dist-info/METADATA
gotennet_pytorch-0.3.1.dist-info/WHEEL
gotennet_pytorch-0.3.1.dist-info/licenses/LICENSE
gotennet_pytorch-0.3.1.dist-info/RECORD
