Metadata-Version: 2.4
Name: gotennet-pytorch
Version: 0.3.1
Summary: GotenNet in Pytorch
Project-URL: Homepage, https://pypi.org/project/gotennet-pytorch/
Project-URL: Repository, https://github.com/lucidrains/gotennet-pytorch
Author-email: Phil Wang <lucidrains@gmail.com>
License: MIT License
License-File: LICENSE
Keywords: artificial intelligence,attention mechanism,deep learning,molecules,se3 equivariance,transformers
Classifier: Development Status :: 4 - Beta
Classifier: Intended Audience :: Developers
Classifier: License :: OSI Approved :: MIT License
Classifier: Programming Language :: Python :: 3.8
Classifier: Topic :: Scientific/Engineering :: Artificial Intelligence
Requires-Python: >=3.9
Requires-Dist: e3nn
Requires-Dist: einops>=0.8.0
Requires-Dist: einx>=0.3.0
Requires-Dist: hyper-connections>=0.1.0
Requires-Dist: jaxtyping
Requires-Dist: torch>=2.4
Requires-Dist: x-transformers>=1.44.4
Provides-Extra: examples
Requires-Dist: numpy; extra == 'examples'
Requires-Dist: tqdm; extra == 'examples'
